setup.py
SpaceObject/Moon.py
SpaceObject/Planet.py
SpaceObject/SpaceObject.py
SpaceObject/__init__.py
SpaceObject.egg-info/PKG-INFO
SpaceObject.egg-info/SOURCES.txt
SpaceObject.egg-info/dependency_links.txt
SpaceObject.egg-info/not-zip-safe
SpaceObject.egg-info/top_level.txt