Metadata-Version: 1.0
Name: SpaceObject
Version: 0.2
Summary: Planets and Moon Objects
Home-page: UNKNOWN
Author: UNKNOWN
Author-email: UNKNOWN
License: UNKNOWN
Platform: UNKNOWN
